Workbook

Sheet интро
C3: Исследование выполнил: Дмитриев Олег
C4: Данные сгенерированы ChatGPT и не являются NDA
C6: Задачи исследования | D6: № | E6: Декомпозиция | F6: Выводы исследования
C7: Анализ продаж продуктовых сетей | D7: 1 | E7: Динамика продаж по магазинам
D8: 2 | E8: Анализ цен внутри товарной категории по магазинам
D9: 3 | E9: Суммарные продажи по магазинам
C10: Сравнение поставщиков по объемам закупок | D10: 4 | E10: Анализ цен внутри категории по поставщикам
D11: 5 | E11: Суммарные продажи по поставщикам
C12: Изучение продаж по категориям товаров | D12: 6 | E12: Суммарные продажи по категориям
D13: 7 | E13: Среднее кол-во по категориям (что покупают чаще)
C14: Изучение клиентов по географии и лайфтайму | D14: 8 | E14: Аналитика географии клиентов
D15: 9 | E15: Кол-во клиентов в программе лояльности
D16: 10 | E16: Кол-во дней с момента регистрации до покупки
D17: 11 | E17: Лайфтайм клиента
D18: 12 | E18: Частотность имен для рекламной компании
D19: 13 | E19: Платежеспособность по странам
C21: Отработка Hard Skills
C22: Преобразование типов и визуальное форматирование
C23: Условное форматирование данных
C24: Умные таблицы и работа с абсолютными и относительными ссылками
C25: Математические и текстовые функции
C26: Функции для работы с датой и временем
C27: Функции поиска и извлечения данных
C28: Сводные таблицы и срезы данных
C29: Построение диаграмм

Sheet Продажи магазинов
A1: магазин покупки | B1: Азбука Вкуса
A3: Названия строк | B3: Сумма по полю сумма чека
A4: 2023
A5: янв | B5: 11705
A6: февр | B6: 10305
A7: март | B7: 22705
A8: апр | B8: 345
A9: май | B9: 21275
A10: июнь | B10: 4920
A11: июль | B11: 5000
A12: авг | B12: 17840
A13: сент | B13: 16435
A14: окт | B14: 5765
A15: нояб | B15: 6945
A16: дек | B16: 1465
A17: 2024
A18: янв | B18: 7650
A19: февр | B19: 18485
A20: март | B20: 19200
A21: апр | B21: 10435
A22: май | B22: 1765

Sheet Выгода клиентам
A3: Названия строк | B3: Среднее по полю Выгода для клиента
A4: Лента | B4: 0.10062699
A5: Седьмой Континент | B5: 0.081840255
A6: Городской Супермаркет | B6: 0.05896841
A7: Билла | B7: 0.056287666
A8: Метро | B8: 0.047135773
A9: Азбука Вкуса | B9: 0.036131084
A10: Мосмарт | B10: 0.023330794
A11: Мираторг | B11: 0.010296277
A12: Карусель | B12: 0.0070069985
A13: Ароматный Мир | B13: 0.0052821685
A14: Бристоль | B14: -0.0080940543
A15: Дикси | B15: -0.009488577
... A23: Пятерочка | B23: -0.10170732

Sheet Суммарные продажи по магазинам
A3: Продуктовая сеть | B3: GMV
A4: О'кей | B4: 264220
A5: Гиперглобус | B5: 258945
A6: Мосмарт | B6: 247900
A7: Спар | B7: 243730
A8: Верный | B8: 235140
A9: Городской Супермаркет | B9: 215490
A10: Ароматный Мир | B10: 214185
A11: Седьмой Континент | B11: 205530
A12: Бристоль | B12: 205050
A13: Мираторг | B13: 200145
A14: Метро | B14: 195840
A15: Лента | B15: 191560
... A24: Общий итог | B24: 4002165

Sheet продажи
A1: id чека | B1: id товара | C1: цена за шт в рублях | D1: кол-во штук в чеке | E1: Сумма чека | F1: дата создания чека | G1: магазин покупки | H1: id клиента | I1: Категория товара | J1: Средняя цена в категории за шт | K1: Выгода для клиента | L1: Поставщик товара | M1: Средняя стоимость в категории по поставщику | N1: Дата регистрации клиента | O1: Кол-во дней с момента регистрации
A2: 1 | B2: 300 | C2: 103 | D2: 4 | E2: =C2*D2 -> 412 | F2: 45187 | G2: Бристоль | H2: 315 | I2: =VLOOKUP(B2,товар!$A$1:$C$433,2,FALSE) -> Сахар | J2: =AVERAGEIF($I$2:$I$1001,I2,$C$2:$C$1001) -> 252.76271 | K2: =C2/J2-1 -> -0.59250319 | L2: =VLOOKUP(B2,товар!$A$1:$C$433,3,FALSE) -> Продимекс | M2: =AVERAGEIFS($C$2:$C$1001,$I$2:$I$1001,I2,$L$2:$L$1001,L2) -> 240.5 | N2: =VLOOKUP(H2,клиенты!$A$1:$G$435,5,FALSE) -> 44747 | O2: =F2-N2 -> 440
A3: 2 | B3: 486 | C3: 296 | D3: 3 | E3: =C3*D3 -> 888 | F3: 45083 | G3: Дикси | H3: 253 | I3: =VLOOKUP(B3,товар!$A$1:$C$433,2,FALSE) -> Соль | J3: =AVERAGEIF($I$2:$I$1001,I3,$C$2:$C$1001) -> 264.86792 | K3: =C3/J3-1 -> 0.11753811 | L3: =VLOOKUP(B3,товар!$A$1:$C$433,3,FALSE) -> Илецкая | M3: =AVERAGEIFS($C$2:$C$1001,$I$2:$I$1001,I3,$L$2:$L$1001,L3) -> 238.16667 | N3: =VLOOKUP(H3,клиенты!$A$1:$G$435,5,FALSE) -> 44750 | O3: =F3-N3 -> 333
A4: 3 | B4: 76 | C4: 139 | D4: 5 | E4: =C4*D4 -> 695 | F4: 45363 | G4: Городской Супермаркет | H4: 12 | I4: =VLOOKUP(B4,товар!$A$1:$C$433,2,FALSE) -> Печенье | J4: =AVERAGEIF($I$2:$I$1001,I4,$C$2:$C$1001) -> 283.46809 | K4: =C4/J4-1 -> -0.50964497 | L4: =VLOOKUP(B4,товар!$A$1:$C$433,3,FALSE) -> Юбилейное | M4: =AVERAGEIFS($C$2:$C$1001,$I$2:$I$1001,I4,$L$2:$L$1001,L4) -> 232.44444 | N4: =VLOOKUP(H4,клиенты!$A$1:$G$435,5,FALSE) -> 44842 | O4: =F4-N4 -> 521
A5: 4 | B5: 240 | C5: 141 | D5: 5 | E5: =C5*D5 -> 705 | F5: 45262 | G5: Верный | H5: 116 | I5: =VLOOKUP(B5,товар!$A$1:$C$433,2,FALSE) -> Макароны | J5: =AVERAGEIF($I$2:$I$1001,I5,$C$2:$C$1001) -> 265.47674 | K5: =C5/J5-1 -> -0.46888003 | L5: =VLOOKUP(B5,товар!$A$1:$C$433,3,FALSE) -> Борилла | M5: =AVERAGEIFS($C$2:$C$1001,$I$2:$I$1001,I5,$L$2:$L$1001,L5) -> 236.27586 | N5: =VLOOKUP(H5,клиенты!$A$1:$G$435,5,FALSE) -> 44643 | O5: =F5-N5 -> 619
A6: 5 | B6: 32 | C6: 123 | D6: 2 | E6: =C6*D6 -> 246 | F6: 45151 | G6: Спар | H6: 471 | I6: =VLOOKUP(B6,товар!$A$1:$C$433,2,FALSE) -> Овощи | J6: =AVERAGEIF($I$2:$I$1001,I6,$C$2:$C$1001) -> 250.4878 | K6: =C6/J6-1 -> -0.50895813 | L6: =VLOOKUP(B6,товар!$A$1:$C$433,3,FALSE) -> Зеленая грядка | M6: =AVERAGEIFS($C$2:$C$1001,$I$2:$I$1001,I6,$L$2:$L$1001,L6) -> 159.2 | N6: =VLOOKUP(H6,клиенты!$A$1:$G$435,5,FALSE) -> 44577 | O6: =F6-N6 -> 574
A7: 6 | B7: 162 | C7: 452 | D7: 2 | E7: =C7*D7 -> 904 | F7: 45281 | G7: Бристоль | H7: 374 | I7: =VLOOKUP(B7,товар!$A$1:$C$433,2,FALSE) -> Сок | J7: =AVERAGEIF($I$2:$I$1001,I7,$C$2:$C$1001) -> 268.60345 | K7: =C7/J7-1 -> 0.6827781 | L7: =VLOOKUP(B7,товар!$A$1:$C$433,3,FALSE) -> Фруктовый сад | M7: =AVERAGEIFS($C$2:$C$1001,$I$2:$I$1001,I7,$L$2:$L$1001,L7) -> 281.96875 | N7: =VLOOKUP(H7,клиенты!$A$1:$G$435,5,FALSE) -> 44582 | O7: =F7-N7 -> 699
A8: 7 | B8: 323 | C8: 149 | D8: 5 | E8: =C8*D8 -> 745 | F8: 45349 | G8: Карусель | H8: 477 | I8: =VLOOKUP(B8,товар!$A$1:$C$433,2,FALSE) -> Рыба | J8: =AVERAGEIF($I$2:$I$1001,I8,$C$2:$C$1001) -> 258.51282 | K8: =C8/J8-1 -> -0.42362626 | L8: =VLOOKUP(B8,товар!$A$1:$C$433,3,FALSE) -> Меридиан | M8: =AVERAGEIFS($C$2:$C$1001,$I$2:$I$1001,I8,$L$2:$L$1001,L8) -> 260.64706 | N8: =VLOOKUP(H8,клиенты!$A$1:$G$435,5,FALSE) -> 44738 | O8: =F8-N8 -> 611
A9: 8 | B9: 60 | C9: 489 | D9: 4 | E9: =C9*D9 -> 1956 | F9: 45327 | G9: Мираторг | H9: 335 | I9: =VLOOKUP(B9,товар!$A$1:$C$433,2,FALSE) -> Кофе | J9: =AVERAGEIF($I$2:$I$1001,I9,$C$2:$C$1001) -> 249.02381 | K9: =C9/J9-1 -> 0.96366765 | L9: =VLOOKUP(B9,товар!$A$1:$C$433,3,FALSE) -> Jacobs | M9: =AVERAGEIFS($C$2:$C$1001,$I$2:$I$1001,I9,$L$2:$L$1001,L9) -> 276.21053 | N9: =VLOOKUP(H9,клиенты!$A$1:$G$435,5,FALSE) -> 44619 | O9: =F9-N9 -> 708
A10: 9 | B10: 401 | C10: 416 | D10: 5 | E10: =C10*D10 -> 2080 | F10: 45376 | G10: Мосмарт | H10: 350 | I10: =VLOOKUP(B10,товар!$A$1:$C$433,2,FALSE) -> Чай | J10: =AVERAGEIF($I$2:$I$1001,I10,$C$2:$C$1001) -> 271.18182 | K10: =C10/J10-1 -> 0.53402615 | L10: =VLOOKUP(B10,товар!$A$1:$C$433,3,FALSE) -> Greenfield | M10: =AVERAGEIFS($C$2:$C$1001,$I$2:$I$1001,I10,$L$2:$L$1001,L10) -> 291.45455 | N10: =VLOOKUP(H10,клиенты!$A$1:$G$435,5,FALSE) -> 44684 | O10: =F10-N10 -> 692
A11: 10 | B11: 100 | C11: 449 | D11: 2 | E11: =C11*D11 -> 898 | F11: 45032 | G11: Карусель | H11: 413 | I11: =VLOOKUP(B11,товар!$A$1:$C$433,2,FALSE) -> Йогурт | J11: =AVERAGEIF($I$2:$I$1001,I11,$C$2:$C$1001) -> 263.25424 | K11: =C11/J11-1 -> 0.70557559 | L11: =VLOOKUP(B11,товар!$A$1:$C$433,3,FALSE) -> Ростагроэкспорт | M11: =AVERAGEIFS($C$2:$C$1001,$I$2:$I$1001,I11,$L$2:$L$1001,L11) -> 257.78261 | N11: =VLOOKUP(H11,клиенты!$A$1:$G$435,5,FALSE) -> 44699 | O11: =F11-N11 -> 333
A12: 11 | B12: 217 | C12: 296 | D12: 2 | E12: =C12*D12 -> 592 | F12: 45136 | G12: Карусель | H12: 495 | I12: =VLOOKUP(B12,товар!$A$1:$C$433,2,FALSE) -> Мясо | J12: =AVERAGEIF($I$2:$I$1001,I12,$C$2:$C$1001) -> 271.74545 | K12: =C12/J12-1 -> 0.08925465 | L12: =VLOOKUP(B12,товар!$A$1:$C$433,3,FALSE) -> Агрокомплекс | M12: =AVERAGEIFS($C$2:$C$1001,$I$2:$I$1001,I12,$L$2:$L$1001,L12) -> 311.2 | N12: =VLOOKUP(H12,клиенты!$A$1:$G$435,5,FALSE) -> 44654 | O12: =F12-N12 -> 482
A13: 12 | B13: 445 | C13: 109 | D13: 5 | E13: =C13*D13 -> 545 | F13: 45394 | G13: Мираторг | H13: 353 | I13: =VLOOKUP(B13,товар!$A$1:$C$433,2,FALSE) -> Сахар | J13: =AVERAGEIF($I$2:$I$1001,I13,$C$2:$C$1001) -> 252.76271 | K13: =C13/J13-1 -> -0.56876551 | L13: =VLOOKUP(B13,товар!$A$1:$C$433,3,FALSE) -> Сладов | M13: =AVERAGEIFS($C$2:$C$1001,$I$2:$I$1001,I13,$L$2:$L$1001,L13) -> 240.26667 | N13: =VLOOKUP(H13,клиенты!$A$1:$G$435,5,FALSE) -> 44656 | O13: =F13-N13 -> 738
... A1001: 1000 | B1001: 296 | C1001: 453 | D1001: 1 | E1001: =C1001*D1001 -> 453 | F1001: 45265 | G1001: Мосмарт | H1001: 167 | I1001: =VLOOKUP(B1001,товар!$A$1:$C$433,2,FALSE) -> Крупа | J1001: =AVERAGEIF($I$2:$I$1001,I1001,$C$2:$C$1001) -> 255.11628 | K1001: =C1001/J1001-1 -> 0.77566089 | L1001: =VLOOKUP(B1001,товар!$A$1:$C$433,3,FALSE) -> Мистраль | M1001: =AVERAGEIFS($C$2:$C$1001,$I$2:$I$1001,I1001,$L$2:$L$1001,L1001) -> 250.30769 | N1001: =VLOOKUP(H1001,клиенты!$A$1:$G$435,5,FALSE) -> 44563 | O1001: =F1001-N1001 -> 702

Sheet товар
A1: id товара | B1: категория товара | C1: поставщик | E1: Категория — поставщик | F1: Количество товаров
A2: 300 | B2: Сахар | C2: Продимекс | E2: Сок — Фруктовый сад | F2: 12
A3: 486 | B3: Соль | C3: Илецкая | E3: Макароны — Паста Зара | F3: 12
A4: 76 | B4: Печенье | C4: Юбилейное | E4: Конфеты — Бабаевский | F4: 12
A5: 240 | B5: Макароны | C5: Борилла | E5: Сыр — Сырная долина | F5: 12
A6: 32 | B6: Овощи | C6: Зеленая грядка | E6: Йогурт — Ростагроэкспорт | F6: 11
A7: 162 | B7: Сок | C7: Фруктовый сад | E7: Макароны — Борилла | F7: 10
A8: 323 | B8: Рыба | C8: Меридиан | E8: Рыба — Меридиан | F8: 9
A9: 60 | B9: Кофе | C9: Jacobs | E9: Чай — Greenfield | F9: 9
A10: 401 | B10: Чай | C10: Greenfield | E10: Конфеты — Рот Фронт | F10: 9
A11: 100 | B11: Йогурт | C11: Ростагроэкспорт | E11: Сок — Добрый | F11: 8
A12: 217 | B12: Мясо | C12: Агрокомплекс | E12: Йогурт — Эрманн | F12: 8
A13: 445 | B13: Сахар | C13: Сладов | E13: Фрукты — Фруктовый Рай | F13: 8
... A16: 378 | B16: Сок | C16: Фруктовый сад | E16: Мясо — Сава | F16: 7
A17: 299 | B17: Чай | C17: Lipton
A18: 359 | B18: Мясо | C18: Мираторг
A19: 337 | B19: Макароны | C19: Паста Зара
A20: 226 | B20: Сыр | C20: Карат
A21: 310 | B21: Макароны | C21: Паста Зара
A22: 137 | B22: Фрукты | C22: Экзотик
A23: 385 | B23: Макароны | C23: Макфа
A24: 451 | B24: Рис | C24: Белый Злат
A25: 7 | B25: Сыр | C25: President
A26: 495 | B26: Чай | C26: Greenfield
A27: 415 | B27: Чипсы | C27: Pringles
A28: 176 | B28: Сахар | C28: Продимекс
... A433: 469 | B433: Сахар | C433: Сладов

Sheet География клиентов
A3: Названия строк | B3: Количество по полю id клиента
A4: Россия | B4: 146
A5: Узбекистан | B5: 85
A6: Украина | B6: 78
A7: Таджикистан | B7: 74
A8: Беларусь | B8: 51
A9: Общий итог | B9: 434

Sheet клиенты
A1: id клиента | B1: номер телефона клиента | C1: ФИО | D1: Программа лояльности клиента | E1: Дата регистрации клиента | F1: Коды телефона | G1: Страна клиента | H1: Имя | I1: Фамилия | J1: Отчество | L1: Страна клиента | M1: Количество клиентов
A2: 315 | B2: +998 469-847-6587 | C2: Фадей Ефимович Калинин | D2: да | E2: 44747 | F2: +998 | G2: Узбекистан | H2: Фадей | I2: Калинин | J2: Ефимович | L2: Россия | M2: 146
A3: 253 | B3: +375 796-304-7865 | C3: Вера Георгиевна Некрасова | D3: да | E3: 44750 | F3: +375 | G3: Беларусь | H3: Вера | I3: Некрасова | J3: Георгиевна | L3: Узбекистан | M3: 85
A4: 12 | B4: +375 682-373-1802 | C4: Никодим Игоревич Бобров | D4: да | E4: 44842 | F4: +375 | G4: Беларусь | H4: Никодим | I4: Бобров | J4: Игоревич | L4: Украина | M4: 78
A5: 116 | B5: +7 753-596-5037 | C5: Носкова Вера Федоровна | D5: нет | E5: 44643 | F5: +7 | G5: Россия | H5: Носкова | I5: Федоровна | J5: Вера | L5: Таджикистан | M5: 74
A6: 471 | B6: +380 669-437-2066 | C6: Александра Матвеевна Артемьева | D6: да | E6: 44577 | F6: +380 | G6: Украина | H6: Александра | I6: Артемьева | J6: Матвеевна | L6: Беларусь | M6: 51
A7: 374 | B7: +380 622-144-1703 | C7: Калинина Ирина Филипповна | D7: нет | E7: 44582 | F7: +380 | G7: Украина | H7: Калинина | I7: Филипповна | J7: Ирина
A8: 477 | B8: +998 591-865-8342 | C8: Зоя Кирилловна Брагина | D8: да | E8: 44738 | F8: +998 | G8: Узбекистан | H8: Зоя | I8: Брагина | J8: Кирилловна
A9: 335 | B9: +998 353-736-8172 | C9: Осипов Светозар Ефремович | D9: нет | E9: 44619 | F9: +998 | G9: Узбекистан | H9: Осипов | I9: Ефремович | J9: Светозар
A10: 350 | B10: +380 545-746-8707 | C10: Любовь Георгиевна Мамонтова | D10: нет | E10: 44684 | F10: +380 | G10: Украина | H10: Любовь | I10: Мамонтова | J10: Георгиевна
A11: 413 | B11: +7 063-931-5918 | C11: Август Вячеславович Брагин | D11: нет | E11: 44699 | F11: +7 | G11: Россия | H11: Август | I11: Брагин | J11: Вячеславович
A12: 495 | B12: +998 006-788-9211 | C12: Мефодий Филиппович Воробьев | D12: да | E12: 44654 | F12: +998 | G12: Узбекистан | H12: Мефодий | I12: Воробьев | J12: Филиппович | L12: Лояльность | M12: Количество
A13: 353 | B13: +992 863-895-4307 | C13: Гурьев Влас Юлианович | D13: да | E13: 44656 | F13: +992 | G13: Таджикистан | H13: Гурьев | I13: Юлианович | J13: Влас | L13: нет | M13: 219
A14: 332 | B14: +998 350-816-0031 | C14: Агата Юрьевна Галкина | D14: нет | E14: 44858 | F14: +998 | G14: Узбекистан | H14: Агата | I14: Галкина | J14: Юрьевна | L14: да | M14: 215
A15: 414 | B15: +375 435-951-1995 | C15: Юлия Леоновна Наумова | D15: нет | E15: 44794 | F15: +375 | G15: Беларусь | H15: Юлия | I15: Наумова | J15: Леоновна
A16: 236 | B16: +998 498-706-1394 | C16: Лонгин Арсенович Никонов | D16: да | E16: 44820 | F16: +998 | G16: Узбекистан | H16: Лонгин | I16: Никонов | J16: Арсенович
A17: 164 | B17: +7 297-169-3756 | C17: Филимон Федотович Иванов | D17: нет | E17: 44678 | F17: +7 | G17: Россия | H17: Филимон | I17: Иванов | J17: Федотович
A18: 490 | B18: +7 454-941-1729 | C18: Кудрявцев Демид Ерофеевич | D18: нет | E18: 44603 | F18: +7 | G18: Россия | H18: Кудрявцев | I18: Ерофеевич | J18: Демид
A19: 223 | B19: +380 835-708-4433 | C19: Вероника Евгеньевна Федосеева | D19: да | E19: 44893 | F19: +380 | G19: Украина | H19: Вероника | I19: Федосеева | J19: Евгеньевна
A20: 204 | B20: +7 181-799-6850 | C20: Герасимов Еремей Демидович | D20: да | E20: 44867 | F20: +7 | G20: Россия | H20: Герасимов | I20: Демидович | J20: Еремей
A21: 481 | B21: +375 743-922-4671 | C21: Новикова Лидия Павловна | D21: да | E21: 44756 | F21: +375 | G21: Беларусь | H21: Новикова | I21: Павловна | J21: Лидия
A22: 363 | B22: +998 607-517-9439 | C22: Сорокина Феврония Натановна | D22: нет | E22: 44675 | F22: +998 | G22: Узбекистан | H22: Сорокина | I22: Натановна | J22: Феврония
A23: 397 | B23: +375 372-396-9651 | C23: Нинель Натановна Лазарева | D23: нет | E23: 44728 | F23: +375 | G23: Беларусь | H23: Нинель | I23: Лазарева | J23: Натановна
A24: 280 | B24: +7 109-995-2846 | C24: г-н Рыбаков Автоном Антонович | D24: нет | E24: 44563 | F24: +7 | G24: Россия | H24: г-н | I24: Автоном Антонович | J24: Рыбаков
A25: 39 | B25: +375 226-887-4565 | C25: Бирюков Олимпий Иосифович | D25: да | E25: 44653 | F25: +375 | G25: Беларусь | H25: Бирюков | I25: Иосифович | J25: Олимпий
A26: 303 | B26: +998 222-956-9780 | C26: Чеслав Виленович Шестаков | D26: нет | E26: 44689 | F26: +998 | G26: Узбекистан | H26: Чеслав | I26: Шестаков | J26: Виленович
... A435: 427 | B435: +7 630-011-3417 | C435: Лидия Андреевна Крюкова | D435: нет | E435: 44834 | F435: +7 | G435: Россия | H435: Лидия | I435: Крюкова | J435: Андреевна

Sheet коды стран
A1: Страна | B1: Код | C1: Количество клиентов
A2: Россия | B2: +7 | C2: 146
A3: Казахстан | B3: +7 | C3: 0
A4: Беларусь | B4: +375 | C4: 51
A5: Узбекистан | B5: +998 | C5: 85
A6: Таджикистан | B6: +992 | C6: 74
A7: Украина | B7: +380 | C7: 78

Sheet Дашборд
A1: Дашборд: товар, клиенты, коды стран
A2: Фильтры: используйте выпадающие фильтры в таблицах-источниках под каждым графиком. Диаграммы построены на сводных источниках данных.
A4: Категория — поставщик | B4: Количество товаров | J4: Всего товаров
A5: Сок — Фруктовый сад | B5: 12 | J5: 432
A6: Макароны — Паста Зара | B6: 12
A7: Конфеты — Бабаевский | B7: 12 | J7: Всего клиентов
A8: Сыр — Сырная долина | B8: 12 | J8: 434
A9: Йогурт — Ростагроэкспорт | B9: 11
A10: Макароны — Борилла | B10: 10 | J10: Стран клиентов
A11: Рыба — Меридиан | B11: 9 | J11: 5
A12: Чай — Greenfield | B12: 9
A13: Конфеты — Рот Фронт | B13: 9 | J13: Топ страна
A14: Сок — Добрый | B14: 8 | J14: Россия (146)
A15: Йогурт — Эрманн | B15: 8
A16: Фрукты — Фруктовый Рай | B16: 8 | J16: Топ связка товара
A17: Сахар — Продимекс | B17: 7 | J17: Сок — Фруктовый сад (12)
A18: Соль — Илецкая | B18: 7
A19: Мясо — Сава | B19: 7
A23: Страна клиента | B23: Количество клиентов | J23: Лояльность | K23: Количество
A24: Россия | B24: 146 | J24: нет | K24: 219
A25: Узбекистан | B25: 85 | J25: да | K25: 215
A26: Украина | B26: 78
A27: Таджикистан | B27: 74
A28: Беларусь | B28: 51
A40: Страна | B40: Код | C40: Количество клиентов
A41: Россия | B41: +7 | C41: 146
A42: Казахстан | B42: +7 | C42: 0
A43: Беларусь | B43: +375 | C43: 51
A44: Узбекистан | B44: +998 | C44: 85
A45: Таджикистан | B45: +992 | C45: 74
A46: Украина | B46: +380 | C46: 78
